LICENSE.txt
README.md
setup.cfg
setup.py
exercise_thirteen.egg-info/PKG-INFO
exercise_thirteen.egg-info/SOURCES.txt
exercise_thirteen.egg-info/dependency_links.txt
exercise_thirteen.egg-info/requires.txt
exercise_thirteen.egg-info/top_level.txt
functions/__init__.py
functions/functions_maths.py
tests/test_functions_maths.py